[
  {
    "title": "Now hiring: Junior Media Strategist",
    "author": "Ibukun Adebolu, PhD",
    "date": "2025-12-26",
    "file": "Career/JuniorMediaStrategist.md",
    "summary": "We are seeking a Junior Media Strategist to support our digital growth initiatives. This role combines social media strategy, paid advertising, SEO optimization, and basic project management to ensure timely delivery and measurable results. It’s ideal for someone passionate about digital marketing and eager to gain hands-on experience in a dynamic, impact-driven environment."
  }
  ]